relai/__init__.py
relai/_client.py
relai/_exceptions.py
relai/benchmark.py
relai/data.py
relai/exporter.py
relai/flags.py
relai/logger.py
relai/simulator.py
relai/utils.py
relai/critico/__init__.py
relai/critico/critico.py
relai/critico/evaluate.py
relai/maestro/__init__.py
relai/maestro/graph.py
relai/maestro/optimizer.py
relai/maestro/params.py
relai/maestro/utils.py
relai/mocker/__init__.py
relai/mocker/base_mocker.py
relai/mocker/persona.py
relai/mocker/tool.py
relai/schema/visual.py
relai-0.3.22.dist-info/licenses/LICENSE.md
relai-0.3.22.dist-info/METADATA
relai-0.3.22.dist-info/WHEEL
relai-0.3.22.dist-info/top_level.txt
relai-0.3.22.dist-info/RECORD
