Metadata-Version: 2.4
Name: relai
Version: 0.3.22
Summary: An SDK for building reliable AI agents
Author-email: RELAI <priyatham@relai.ai>, RELAI <wwx@relai.ai>
License:                                 Apache License
Classifier: License :: OSI Approved :: Apache Software License
Classifier: Development Status :: 4 - Beta
Classifier: Programming Language :: Python :: 3.10
Classifier: Programming Language :: Python :: 3.11
Classifier: Programming Language :: Python :: 3.12
Classifier: Programming Language :: Python :: 3.13
Requires-Python: >=3.10
License-File: LICENSE.md
Requires-Dist: pydantic>=2.11.5
Requires-Dist: numpy>=1.26.4
Requires-Dist: aiohttp[speedups]>=3.12.15
Requires-Dist: httpx>=0.28.1
Requires-Dist: openai-agents[litellm]>=0.2.10
Requires-Dist: opentelemetry-instrumentation>=0.58b0
Requires-Dist: openinference-instrumentation>=0.1.38
Dynamic: license-file
